geode_moduletemplate/__init__.py
geode_moduletemplate/geode_mymodule_py_mylib.cpython-39-x86_64-linux-gnu.so
geode_moduletemplate/libGeode-MyModule_mylib.so
geode_moduletemplate/mylib.py
Geode_ModuleTemplate-1.1.0.dist-info/METADATA
Geode_ModuleTemplate-1.1.0.dist-info/WHEEL
Geode_ModuleTemplate-1.1.0.dist-info/top_level.txt
Geode_ModuleTemplate-1.1.0.dist-info/RECORD
