Metadata-Version: 2.1
Name: Geode-ModuleTemplate
Version: 1.1.0
Summary: Template for creating your own OpenGeode private module
Home-page: https://github.com/Geode-solutions/Geode-ModuleTemplate
Author: Geode-solutions
Author-email: contact@geode-solutions.com
License: Proprietary
Requires-Dist: OpenGeode-core (==12.*,>=12.1.8)
Requires-Dist: Geode-Common (==23.*,>=23.1.4)
